dxf_frame_generator.py
dxf_frame_generator-0.0.1.dist-info/LICENSE
dxf_frame_generator-0.0.1.dist-info/METADATA
dxf_frame_generator-0.0.1.dist-info/WHEEL
dxf_frame_generator-0.0.1.dist-info/entry_points.txt
dxf_frame_generator-0.0.1.dist-info/top_level.txt
dxf_frame_generator-0.0.1.dist-info/RECORD
