Metadata-Version: 2.1
Name: dxf-frame-generator
Version: 0.0.1
Summary: Custom sized frames for digital fabrication.
Home-page: https://github.com/umluizlima/dxf-frame-generator
Author: Luiz Lima
Author-email: umluizlima@gmail.com
License: MIT License
Platform: UNKNOWN
Classifier: Programming Language :: Python :: 3
Classifier: License :: OSI Approved :: MIT License
Classifier: Operating System :: OS Independent
Requires-Dist: ezdxf
